dekeyrej_pages-0.5.13.dist-info/licenses/LICENSE
pages/__init__.py
pages/displaypage.py
pages/serverpage.py
dekeyrej_pages-0.5.13.dist-info/METADATA
dekeyrej_pages-0.5.13.dist-info/WHEEL
dekeyrej_pages-0.5.13.dist-info/top_level.txt
dekeyrej_pages-0.5.13.dist-info/RECORD
