Metadata-Version: 2.4
Name: dekeyrej-pages
Version: 0.5.13
Summary: base classes for microservice servers and matrix display pages
Author: J.DeKeyrel
Author-email: "J. DeKeyrel" <noneyabusiness@notemail.com>
License: MIT License
Classifier: License :: OSI Approved :: MIT License
Classifier: Programming Language :: Python
Classifier: Programming Language :: Python :: 3
Requires-Python: >=3.9
License-File: LICENSE
Requires-Dist: arrow
Requires-Dist: dekeyrej-datasource
Requires-Dist: dekeyrej-kube
Requires-Dist: requests
Dynamic: author
Dynamic: license-file
